segdisplaydecoder/BCD7segD.py
segdisplaydecoder/__init__.py
segdisplaydecoder-1.0.1.dist-info/LICENSE
segdisplaydecoder-1.0.1.dist-info/METADATA
segdisplaydecoder-1.0.1.dist-info/WHEEL
segdisplaydecoder-1.0.1.dist-info/top_level.txt
segdisplaydecoder-1.0.1.dist-info/RECORD
